{
 "cells": [
  {
   "cell_type": "code",
   "execution_count": 8,
   "metadata": {},
   "outputs": [
    {
     "data": {
      "text/plain": [
       "[0, 1, 4, 9, 16, 25, 36]"
      ]
     },
     "execution_count": 8,
     "metadata": {},
     "output_type": "execute_result"
    }
   ],
   "source": [
    "l=[i**2 for i in range(7)]\n",
    "l"
   ]
  },
  {
   "cell_type": "code",
   "execution_count": 9,
   "metadata": {},
   "outputs": [
    {
     "data": {
      "text/plain": [
       "[0, 1, 4, 9, 16, 25, 36]"
      ]
     },
     "execution_count": 9,
     "metadata": {},
     "output_type": "execute_result"
    }
   ],
   "source": [
    "l"
   ]
  },
  {
   "cell_type": "code",
   "execution_count": 10,
   "metadata": {},
   "outputs": [],
   "source": [
    "g=(i**2 for i in range(7))"
   ]
  },
  {
   "cell_type": "code",
   "execution_count": 11,
   "metadata": {},
   "outputs": [
    {
     "data": {
      "text/plain": [
       "generator"
      ]
     },
     "execution_count": 11,
     "metadata": {},
     "output_type": "execute_result"
    }
   ],
   "source": [
    "type(g)"
   ]
  },
  {
   "cell_type": "code",
   "execution_count": 12,
   "metadata": {},
   "outputs": [
    {
     "name": "stdout",
     "output_type": "stream",
     "text": [
      "<generator object <genexpr> at 0x000001FF46EB2E30>\n"
     ]
    }
   ],
   "source": [
    "print(g)"
   ]
  },
  {
   "cell_type": "code",
   "execution_count": 13,
   "metadata": {},
   "outputs": [
    {
     "name": "stdout",
     "output_type": "stream",
     "text": [
      "0\n",
      "1\n",
      "4\n",
      "9\n",
      "16\n",
      "25\n",
      "36\n"
     ]
    }
   ],
   "source": [
    "for i in g :\n",
    "    print(i)"
   ]
  },
  {
   "cell_type": "code",
   "execution_count": 14,
   "metadata": {},
   "outputs": [],
   "source": [
    "for i in g:\n",
    "    print(i)"
   ]
  },
  {
   "cell_type": "code",
   "execution_count": 15,
   "metadata": {},
   "outputs": [],
   "source": [
    "import dis"
   ]
  },
  {
   "cell_type": "code",
   "execution_count": 18,
   "metadata": {},
   "outputs": [],
   "source": [
    "exp=compile('[i**2 for i in range(5)]', filename='<string>', mode='eval')"
   ]
  },
  {
   "cell_type": "code",
   "execution_count": 19,
   "metadata": {},
   "outputs": [
    {
     "name": "stdout",
     "output_type": "stream",
     "text": [
      "  1           0 LOAD_CONST               0 (<code object <listcomp> at 0x000001FF4549DC60, file \"<string>\", line 1>)\n",
      "              2 LOAD_CONST               1 ('<listcomp>')\n",
      "              4 MAKE_FUNCTION            0\n",
      "              6 LOAD_NAME                0 (range)\n",
      "              8 LOAD_CONST               2 (5)\n",
      "             10 CALL_FUNCTION            1\n",
      "             12 GET_ITER\n",
      "             14 CALL_FUNCTION            1\n",
      "             16 RETURN_VALUE\n",
      "\n",
      "Disassembly of <code object <listcomp> at 0x000001FF4549DC60, file \"<string>\", line 1>:\n",
      "  1           0 BUILD_LIST               0\n",
      "              2 LOAD_FAST                0 (.0)\n",
      "        >>    4 FOR_ITER                 6 (to 18)\n",
      "              6 STORE_FAST               1 (i)\n",
      "              8 LOAD_FAST                1 (i)\n",
      "             10 LOAD_CONST               0 (2)\n",
      "             12 BINARY_POWER\n",
      "             14 LIST_APPEND              2\n",
      "             16 JUMP_ABSOLUTE            2 (to 4)\n",
      "        >>   18 RETURN_VALUE\n"
     ]
    }
   ],
   "source": [
    "dis.dis(exp)"
   ]
  },
  {
   "cell_type": "code",
   "execution_count": 20,
   "metadata": {},
   "outputs": [],
   "source": [
    "exp=compile('(i**2 for i in range(5))', filename='<string>', mode='eval')"
   ]
  },
  {
   "cell_type": "code",
   "execution_count": 21,
   "metadata": {},
   "outputs": [
    {
     "name": "stdout",
     "output_type": "stream",
     "text": [
      "  1           0 LOAD_CONST               0 (<code object <genexpr> at 0x000001FF45105C60, file \"<string>\", line 1>)\n",
      "              2 LOAD_CONST               1 ('<genexpr>')\n",
      "              4 MAKE_FUNCTION            0\n",
      "              6 LOAD_NAME                0 (range)\n",
      "              8 LOAD_CONST               2 (5)\n",
      "             10 CALL_FUNCTION            1\n",
      "             12 GET_ITER\n",
      "             14 CALL_FUNCTION            1\n",
      "             16 RETURN_VALUE\n",
      "\n",
      "Disassembly of <code object <genexpr> at 0x000001FF45105C60, file \"<string>\", line 1>:\n",
      "              0 GEN_START                0\n",
      "\n",
      "  1           2 LOAD_FAST                0 (.0)\n",
      "        >>    4 FOR_ITER                 7 (to 20)\n",
      "              6 STORE_FAST               1 (i)\n",
      "              8 LOAD_FAST                1 (i)\n",
      "             10 LOAD_CONST               0 (2)\n",
      "             12 BINARY_POWER\n",
      "             14 YIELD_VALUE\n",
      "             16 POP_TOP\n",
      "             18 JUMP_ABSOLUTE            2 (to 4)\n",
      "        >>   20 LOAD_CONST               1 (None)\n",
      "             22 RETURN_VALUE\n"
     ]
    }
   ],
   "source": [
    "dis.dis(exp)"
   ]
  },
  {
   "cell_type": "code",
   "execution_count": 22,
   "metadata": {},
   "outputs": [],
   "source": [
    "l=[i for i in range(7)]"
   ]
  },
  {
   "cell_type": "code",
   "execution_count": 23,
   "metadata": {},
   "outputs": [
    {
     "data": {
      "text/plain": [
       "list"
      ]
     },
     "execution_count": 23,
     "metadata": {},
     "output_type": "execute_result"
    }
   ],
   "source": [
    "type(l)"
   ]
  },
  {
   "cell_type": "code",
   "execution_count": 24,
   "metadata": {},
   "outputs": [],
   "source": [
    "g=(i for i in range(7))"
   ]
  },
  {
   "cell_type": "code",
   "execution_count": 25,
   "metadata": {},
   "outputs": [
    {
     "data": {
      "text/plain": [
       "generator"
      ]
     },
     "execution_count": 25,
     "metadata": {},
     "output_type": "execute_result"
    }
   ],
   "source": [
    "type(g)"
   ]
  },
  {
   "cell_type": "code",
   "execution_count": 26,
   "metadata": {},
   "outputs": [
    {
     "data": {
      "text/plain": [
       "[[1, 2, 3, 4, 5, 6, 7, 8, 9, 10],\n",
       " [2, 4, 6, 8, 10, 12, 14, 16, 18, 20],\n",
       " [3, 6, 9, 12, 15, 18, 21, 24, 27, 30],\n",
       " [4, 8, 12, 16, 20, 24, 28, 32, 36, 40],\n",
       " [5, 10, 15, 20, 25, 30, 35, 40, 45, 50],\n",
       " [6, 12, 18, 24, 30, 36, 42, 48, 54, 60],\n",
       " [7, 14, 21, 28, 35, 42, 49, 56, 63, 70],\n",
       " [8, 16, 24, 32, 40, 48, 56, 64, 72, 80],\n",
       " [9, 18, 27, 36, 45, 54, 63, 72, 81, 90],\n",
       " [10, 20, 30, 40, 50, 60, 70, 80, 90, 100]]"
      ]
     },
     "execution_count": 26,
     "metadata": {},
     "output_type": "execute_result"
    }
   ],
   "source": [
    "start=1\n",
    "stop=10\n",
    "\n",
    "l=[[i*j for j in range(start , stop+1)] for i in range(start,stop+1)]\n",
    "l"
   ]
  },
  {
   "cell_type": "code",
   "execution_count": 38,
   "metadata": {},
   "outputs": [],
   "source": [
    "start=1\n",
    "stop=10\n",
    "\n",
    "g=((i*j for j in range(start , stop+1)) for i in range(start,stop+1))\n"
   ]
  },
  {
   "cell_type": "code",
   "execution_count": 39,
   "metadata": {},
   "outputs": [
    {
     "data": {
      "text/plain": [
       "<generator object <genexpr> at 0x000001FF46FE31B0>"
      ]
     },
     "execution_count": 39,
     "metadata": {},
     "output_type": "execute_result"
    }
   ],
   "source": [
    "g"
   ]
  },
  {
   "cell_type": "code",
   "execution_count": 40,
   "metadata": {},
   "outputs": [
    {
     "data": {
      "text/plain": [
       "[[1, 2, 3, 4, 5, 6, 7, 8, 9, 10],\n",
       " [2, 4, 6, 8, 10, 12, 14, 16, 18, 20],\n",
       " [3, 6, 9, 12, 15, 18, 21, 24, 27, 30],\n",
       " [4, 8, 12, 16, 20, 24, 28, 32, 36, 40],\n",
       " [5, 10, 15, 20, 25, 30, 35, 40, 45, 50],\n",
       " [6, 12, 18, 24, 30, 36, 42, 48, 54, 60],\n",
       " [7, 14, 21, 28, 35, 42, 49, 56, 63, 70],\n",
       " [8, 16, 24, 32, 40, 48, 56, 64, 72, 80],\n",
       " [9, 18, 27, 36, 45, 54, 63, 72, 81, 90],\n",
       " [10, 20, 30, 40, 50, 60, 70, 80, 90, 100]]"
      ]
     },
     "execution_count": 40,
     "metadata": {},
     "output_type": "execute_result"
    }
   ],
   "source": [
    "l=[list(i) for i in g]\n",
    "l"
   ]
  },
  {
   "cell_type": "code",
   "execution_count": 41,
   "metadata": {},
   "outputs": [],
   "source": [
    "start=1\n",
    "stop=10\n",
    "\n",
    "g=([ i*j for j in range(start,stop)] for i in range(start,stop+1))"
   ]
  },
  {
   "cell_type": "code",
   "execution_count": 42,
   "metadata": {},
   "outputs": [
    {
     "name": "stdout",
     "output_type": "stream",
     "text": [
      "[1, 2, 3, 4, 5, 6, 7, 8, 9]\n",
      "[2, 4, 6, 8, 10, 12, 14, 16, 18]\n",
      "[3, 6, 9, 12, 15, 18, 21, 24, 27]\n",
      "[4, 8, 12, 16, 20, 24, 28, 32, 36]\n",
      "[5, 10, 15, 20, 25, 30, 35, 40, 45]\n",
      "[6, 12, 18, 24, 30, 36, 42, 48, 54]\n",
      "[7, 14, 21, 28, 35, 42, 49, 56, 63]\n",
      "[8, 16, 24, 32, 40, 48, 56, 64, 72]\n",
      "[9, 18, 27, 36, 45, 54, 63, 72, 81]\n",
      "[10, 20, 30, 40, 50, 60, 70, 80, 90]\n"
     ]
    }
   ],
   "source": [
    "for i in g:\n",
    "    print(i)"
   ]
  },
  {
   "cell_type": "code",
   "execution_count": 71,
   "metadata": {},
   "outputs": [],
   "source": [
    "from math import factorial\n",
    "g=((factorial(i)//(factorial(j)* factorial(i-j)) for j in range(i+1)) for i in range(10))"
   ]
  },
  {
   "cell_type": "code",
   "execution_count": 72,
   "metadata": {},
   "outputs": [
    {
     "data": {
      "text/plain": [
       "<generator object <genexpr> at 0x000001FF46FEAC00>"
      ]
     },
     "execution_count": 72,
     "metadata": {},
     "output_type": "execute_result"
    }
   ],
   "source": [
    "g"
   ]
  },
  {
   "cell_type": "code",
   "execution_count": 73,
   "metadata": {},
   "outputs": [],
   "source": [
    "l=[list(i) for i in g]"
   ]
  },
  {
   "cell_type": "code",
   "execution_count": 74,
   "metadata": {},
   "outputs": [
    {
     "data": {
      "text/plain": [
       "[[1],\n",
       " [1, 1],\n",
       " [1, 2, 1],\n",
       " [1, 3, 3, 1],\n",
       " [1, 4, 6, 4, 1],\n",
       " [1, 5, 10, 10, 5, 1],\n",
       " [1, 6, 15, 20, 15, 6, 1],\n",
       " [1, 7, 21, 35, 35, 21, 7, 1],\n",
       " [1, 8, 28, 56, 70, 56, 28, 8, 1],\n",
       " [1, 9, 36, 84, 126, 126, 84, 36, 9, 1]]"
      ]
     },
     "execution_count": 74,
     "metadata": {},
     "output_type": "execute_result"
    }
   ],
   "source": [
    "l"
   ]
  },
  {
   "cell_type": "code",
   "execution_count": 75,
   "metadata": {},
   "outputs": [],
   "source": [
    "from math import factorial\n",
    "l=[[factorial(i)//(factorial(j)* factorial(i-j)) for j in range(i+1)] for i in range(10)]"
   ]
  },
  {
   "cell_type": "code",
   "execution_count": 76,
   "metadata": {},
   "outputs": [
    {
     "data": {
      "text/plain": [
       "[[1],\n",
       " [1, 1],\n",
       " [1, 2, 1],\n",
       " [1, 3, 3, 1],\n",
       " [1, 4, 6, 4, 1],\n",
       " [1, 5, 10, 10, 5, 1],\n",
       " [1, 6, 15, 20, 15, 6, 1],\n",
       " [1, 7, 21, 35, 35, 21, 7, 1],\n",
       " [1, 8, 28, 56, 70, 56, 28, 8, 1],\n",
       " [1, 9, 36, 84, 126, 126, 84, 36, 9, 1]]"
      ]
     },
     "execution_count": 76,
     "metadata": {},
     "output_type": "execute_result"
    }
   ],
   "source": [
    "l"
   ]
  },
  {
   "cell_type": "code",
   "execution_count": null,
   "metadata": {},
   "outputs": [],
   "source": []
  }
 ],
 "metadata": {
  "kernelspec": {
   "display_name": "Python 3",
   "language": "python",
   "name": "python3"
  },
  "language_info": {
   "codemirror_mode": {
    "name": "ipython",
    "version": 3
   },
   "file_extension": ".py",
   "mimetype": "text/x-python",
   "name": "python",
   "nbconvert_exporter": "python",
   "pygments_lexer": "ipython3",
   "version": "3.10.4"
  },
  "orig_nbformat": 4
 },
 "nbformat": 4,
 "nbformat_minor": 2
}
